setup.py
pyipayment/__init__.py
pyipayment.egg-info/PKG-INFO
pyipayment.egg-info/SOURCES.txt
pyipayment.egg-info/dependency_links.txt
pyipayment.egg-info/not-zip-safe
pyipayment.egg-info/top_level.txt