Metadata-Version: 1.1
Name: pyipayment
Version: 0.1.0
Summary: Python iPayment API
Home-page: http://github.com/tachang/pyipayment/
Author: Jeff Tchang
Author-email: jeff.tchang@gmail.com
License: UNKNOWN
Platform: UNKNOWN
Classifier: Development Status :: 4 - Beta
Classifier: Intended Audience :: Developers
Classifier: License :: OSI Approved :: BSD License
Classifier: Operating System :: OS Independent
Classifier: Programming Language :: Python
Classifier: Topic :: Utilities
